LICENSE
MANIFEST.in
setup.cfg
setup.py
archipel_agent_vmcasting.egg-info/PKG-INFO
archipel_agent_vmcasting.egg-info/SOURCES.txt
archipel_agent_vmcasting.egg-info/dependency_links.txt
archipel_agent_vmcasting.egg-info/entry_points.txt
archipel_agent_vmcasting.egg-info/not-zip-safe
archipel_agent_vmcasting.egg-info/requires.txt
archipel_agent_vmcasting.egg-info/top_level.txt
archipelagentvmcasting/__init__.py
archipelagentvmcasting/__init__.pyc
archipelagentvmcasting/appliancecompresser.py
archipelagentvmcasting/appliancecompresser.pyc
archipelagentvmcasting/appliancedecompresser.py
archipelagentvmcasting/appliancedecompresser.pyc
archipelagentvmcasting/hypervisorrepomanager.py
archipelagentvmcasting/hypervisorrepomanager.pyc
archipelagentvmcasting/vmappliancemanager.py
archipelagentvmcasting/vmappliancemanager.pyc
archipelagentvmcasting/vmcastmaker.py
archipelagentvmcasting/vmcastmaker.pyc